magneto_pyelastica/__init__.py
magneto_pyelastica/magnetic_field.py
magneto_pyelastica/magnetic_forces.py
magneto_pyelastica/utils.py
magneto_pyelastica/version.py
magneto_pyelastica-0.0.1.post2.dist-info/LICENSE
magneto_pyelastica-0.0.1.post2.dist-info/METADATA
magneto_pyelastica-0.0.1.post2.dist-info/WHEEL
magneto_pyelastica-0.0.1.post2.dist-info/RECORD
