Metadata-Version: 2.1
Name: magneto-pyelastica
Version: 0.0.1.post2
Summary: Python software for simulating magnetic Cosserat rods.
Home-page: https://github.com/armantekinalp/MagnetoPyElastica
License: MIT
Keywords: python,simulation,elastica,cosserat-rod,magneto-elastodynamics
Author: Arman Tekinalp
Author-email: armant2@illinois.edu
Requires-Python: >=3.8,<3.11
Classifier: License :: OSI Approved :: MIT License
Classifier: Programming Language :: Python :: 3
Classifier: Programming Language :: Python :: 3.8
Classifier: Programming Language :: Python :: 3.9
Classifier: Programming Language :: Python :: 3.10
Provides-Extra: examples
Requires-Dist: matplotlib (>=3.3.2,<4.0.0) ; extra == "examples"
Requires-Dist: pyelastica (>=0.3,<0.4)
Project-URL: Repository, https://github.com/armantekinalp/MagnetoPyElastica
